{
  "id": "champ-000419",
  "name": "Джинсы",
  "url": "",
  "parent": "Мужская одежда",
  "parentId": "champ-000416",
  "oneCId": "419",
  "sortOrder": 2300203,
  "active": true,
  "showHome": false,
  "mainImageName": "",
  "iconName": "",
  "source": "the-champ",
  "champId": 419,
  "depth": 3,
  "path": "Одежда / Мужская одежда / Джинсы",
  "createdAt": "2026-05-28T19:02:33",
  "priorityGroup": 3,
  "folderPath": "C:\\Users\\Crypt\\Documents\\TheChamp\\katalog\\Категории\\Одежда\\Мужская одежда\\Джинсы"
}